greeneye/__init__.py
greeneye/api.py
greeneye/monitor.py
greeneye/protocol.py
greeneye/py.typed
greeneye_monitor-5.0.2.dist-info/LICENSE
greeneye_monitor-5.0.2.dist-info/METADATA
greeneye_monitor-5.0.2.dist-info/WHEEL
greeneye_monitor-5.0.2.dist-info/RECORD
