Metadata-Version: 2.1
Name: greeneye_monitor
Version: 5.0.2
Summary: Receive data packets from GreenEye Monitor (http://www.brultech.com/greeneye/)
Home-page: https://github.com/jkeljo/greeneye-monitor
License: MIT
Keywords: greeneye
Author: Jonathan Keljo
Requires-Python: >=3.10,<4.0
Classifier: Development Status :: 4 - Beta
Classifier: Intended Audience :: Developers
Classifier: License :: OSI Approved :: MIT License
Classifier: Programming Language :: Python :: 3
Classifier: Programming Language :: Python :: 3.10
Classifier: Programming Language :: Python :: 3.11
Classifier: Programming Language :: Python :: 3.12
Classifier: Topic :: Home Automation
Requires-Dist: aiohttp (>=3.8.5,<4.0.0)
Requires-Dist: siobrultech-protocols (==0.13)
Project-URL: Repository, https://github.com/jkeljo/greeneye-monitor
